poe_market_book/__init__.py
poe_market_book-0.0.1.dist-info/METADATA
poe_market_book-0.0.1.dist-info/WHEEL
poe_market_book-0.0.1.dist-info/licenses/LICENSE
poe_market_book-0.0.1.dist-info/RECORD
